middoe/__init__.py
middoe/des_md.py
middoe/des_pp.py
middoe/des_utils.py
middoe/iden_parmest.py
middoe/iden_uncert.py
middoe/iden_utils.py
middoe/iden_valida.py
middoe/krnl_expera.py
middoe/krnl_models.py
middoe/krnl_simula.py
middoe/log_utils.py
middoe/sc_estima.py
middoe/sc_sensa.py
middoe-0.0.48.dist-info/LICENSE
middoe-0.0.48.dist-info/METADATA
middoe-0.0.48.dist-info/WHEEL
middoe-0.0.48.dist-info/RECORD
