Metadata-Version: 2.3
Name: middoe
Version: 0.0.48
Summary: Model Identification, Discrimination, and Design of Experiments.
License: MIT
Author: Zuhair Tabrizi
Author-email: zuhairtabrizi@gmail.com
Requires-Python: >=3.9,<3.14
Classifier: License :: OSI Approved :: MIT License
Classifier: Programming Language :: Python :: 3
Classifier: Programming Language :: Python :: 3.9
Classifier: Programming Language :: Python :: 3.10
Classifier: Programming Language :: Python :: 3.11
Classifier: Programming Language :: Python :: 3.12
Classifier: Programming Language :: Python :: 3.13
Requires-Dist: XlsxWriter (>=3.2.3,<4.0.0)
Requires-Dist: matplotlib (<=3.10.1)
Requires-Dist: numpy (<=2.2.3)
Requires-Dist: openpyxl (>=3.1.5,<4.0.0)
Requires-Dist: pandas (<=2.2.3)
Requires-Dist: pendulum (>=3.0.0)
Requires-Dist: pymoo (>=0.6.1.3,<0.7.0.0)
Requires-Dist: scipy (<=1.15.2)
Project-URL: Repository, https://github.com/zuhairblr/middoe/
